qcloud_cos/__init__.py
qcloud_cos/cos_auth.py
qcloud_cos/cos_client.py
qcloud_cos/cos_config.py
qcloud_cos/cos_cred.py
qcloud_cos/cos_err.py
qcloud_cos/cos_op.py
qcloud_cos/cos_params_check.py
qcloud_cos/cos_request.py
qcloud_cos_python3-3.3.6.dist-info/METADATA
qcloud_cos_python3-3.3.6.dist-info/WHEEL
qcloud_cos_python3-3.3.6.dist-info/top_level.txt
qcloud_cos_python3-3.3.6.dist-info/RECORD
